pyryd/__init__.py
pyryd/pyryd.py
PyRYD-0.1.5.dist-info/LICENSE
PyRYD-0.1.5.dist-info/METADATA
PyRYD-0.1.5.dist-info/WHEEL
PyRYD-0.1.5.dist-info/top_level.txt
PyRYD-0.1.5.dist-info/RECORD
