Metadata-Version: 2.1
Name: PyRYD
Version: 0.1.5
Summary: python variant to read data from RYD (previously known as TankTaler) ODB2 Adapter
Home-page: https://github.com/Yannik25/pyryd
Author: Yannik25
Author-email: yannik92@me.com
License: MIT
Keywords: python ryd tanktaler home automation car obd adapter
Classifier: Programming Language :: Python :: 3
Classifier: License :: OSI Approved :: MIT License
Classifier: Operating System :: OS Independent
Requires-Python: >=3
License-File: LICENSE
Requires-Dist: requests
